[
  {
    "id": "1",
    "brand": "BYD",
    "model": "Seal U",
    "image": "resimler/ioniq5-2024-og.jpg",
    "content": "BYD Seal U, geniş iç hacmi ve 500 km menziliyle aileler için ideal bir elektrikli SUV'dur. Modern teknolojiler ve konforu bir arada sunar."
  },
  {
    "id": "2",
    "brand": "Mercedes-Benz",
    "model": "EQS 2025",
    "image": "resimler/2025-mercedes-benz-eqs-exterior-113-6616f12b6d591.avif",
    "content": "Mercedes-Benz EQS 2025, lüks ve performansı bir arada sunan, 780 km menzile sahip elektrikli bir sedan modelidir."
  },
  {
    "id": "3",
    "brand": "Tesla",
    "model": "Model Y",
    "image": "resimler/tesla-model-y-inceleme.jpg__i=AA",
    "content": "Tesla Model Y, yüksek menzilwwi ve gelişmiş otonom sürüş özellikleriyle öne çıkan, aileler için uygun bir elektrikli SUV'dur."
  },
  {
    "id": "4",
    "brand": "BMW",
    "model": "iX",
    "image": "resimler/BMW_iX_IAA_2021_1X7A0204.jpg",
    "content": "BMW iX, 630 km menzili ve lüks donanımıyla uzun yolculuklar için tasarlanmış, ileri teknolojiye sahip bir elektrikli SUV'dur."
  },
  {
    "id": "5",
    "brand": "Audi",
    "model": "e-tron Sportback",
    "image": "resimler/2020-Audi-E-Tron-Sportback-11.jpg",
    "content": "Audi e-tron Sportback, sportif tasarımı ve 440 km menziliyle şehir içi ve uzun yol kullanımı için uygundur."
  },
  {
    "id": "6",
    "brand": "Volkswagen",
    "model": "ID.4",
    "image": "resimler/2021-volkswagen-id.4-exterior-in-motion.jpg",
    "content": "Volkswagen ID.4, modern tasarımı ve 520 km menziliyle şehir içi ve uzun yolculuklar için ideal bir elektrikli SUV'dur."
  },
  {
    "id": "1752529210567",
    "brand": "er",
    "model": "er",
    "content": "erer",
    "trdeVar": false,
    "image": "/backend/uploads/1752529210561-825643928.jpg"
  },
  {
    "id": "1752529211326",
    "brand": "er",
    "model": "er",
    "content": "erer",
    "trdeVar": false,
    "image": "/backend/uploads/1752529211322-310352680.jpg"
  },
  {
    "id": "1752529420867",
    "brand": "fea",
    "model": "ef",
    "content": "ef",
    "trdeVar": false,
    "image": ""
  },
  {
    "id": "1752529421055",
    "brand": "fea",
    "model": "ef",
    "content": "ef",
    "trdeVar": false,
    "image": ""
  },
  {
    "id": "1752529424637",
    "brand": "fea",
    "model": "ef",
    "content": "ef",
    "trdeVar": false,
    "image": "/backend/uploads/1752529424635-713756939.ico"
  },
  {
    "id": "1752529424884",
    "brand": "fea",
    "model": "ef",
    "content": "ef",
    "trdeVar": false,
    "image": "/backend/uploads/1752529424883-216658688.ico"
  }
]